prestream/__init__.py
prestream/prestream.py
prestream-0.1.dist-info/LICENSE
prestream-0.1.dist-info/METADATA
prestream-0.1.dist-info/WHEEL
prestream-0.1.dist-info/entry_points.txt
prestream-0.1.dist-info/top_level.txt
prestream-0.1.dist-info/RECORD
