Metadata-Version: 2.1
Name: prestream
Version: 0.1
Summary: Interactive script for streaming with yt-dlp and ffmpeg.
Home-page: https://x.com/Lanaev0li
Author: Avinion Group
Author-email: shizofrin@gmail.com
License-File: LICENSE
Requires-Dist: yt-dlp
Requires-Dist: ffmpeg-python
